api/__init__.py
api/api_v1/__init__.py
api/api_v1/endpoints/__init__.py
api/api_v1/endpoints/logic_synthesis.py
boolean_solver/__init__.py
boolean_solver/main.py
boolean_solver/program1.py
boolean_solver_gui-0.1.0.dist-info/LICENSE
boolean_solver_gui-0.1.0.dist-info/METADATA
boolean_solver_gui-0.1.0.dist-info/WHEEL
boolean_solver_gui-0.1.0.dist-info/entry_points.txt
boolean_solver_gui-0.1.0.dist-info/top_level.txt
boolean_solver_gui-0.1.0.dist-info/RECORD
