Metadata-Version: 2.1
Name: boolean_solver_gui
Version: 0.1.0
Summary: A simple boolean algebra solver with gui
Home-page: http://github.com/yourusername/your_package
Author: Aidan Nowakowski
Author-email: aidannow@bu.edu
Classifier: Programming Language :: Python :: 3
Classifier: License :: OSI Approved :: MIT License
Classifier: Operating System :: OS Independent
License-File: LICENSE
Requires-Dist: sympy
Requires-Dist: quine-mccluskey
